{
  "annotations": {
    "list": [
      {
        "builtIn": 1,
        "datasource": {
          "type": "grafana",
          "uid": "-- Grafana --"
        },
        "enable": true,
        "hide": true,
        "iconColor": "rgba(0, 211, 255, 1)",
        "name": "Annotations & Alerts",
        "type": "dashboard"
      }
    ]
  },
  "editable": true,
  "fiscalYearStartMonth": 0,
  "graphTooltip": 0,
  "id": 3,
  "links": [],
  "panels": [
    {
      "datasource": {
        "default": true,
        "type": "influxdb",
        "uid": "bf4fhga3fgvswc"
      },
      "description": "",
      "fieldConfig": {
        "defaults": {
          "color": {
            "mode": "thresholds"
          },
          "mappings": [
            {
              "options": {
                "off": {
                  "color": "red",
                  "index": 1,
                  "text": "Offline"
                },
                "on": {
                  "color": "green",
                  "index": 0,
                  "text": "Online"
                }
              },
              "type": "value"
            }
          ],
          "thresholds": {
            "mode": "absolute",
            "steps": [
              {
                "color": "green",
                "value": null
              }
            ]
          }
        },
        "overrides": []
      },
      "gridPos": {
        "h": 8,
        "w": 12,
        "x": 0,
        "y": 0
      },
      "id": 5,
      "options": {
        "colorMode": "value",
        "graphMode": "area",
        "justifyMode": "auto",
        "orientation": "auto",
        "percentChangeColorMode": "standard",
        "reduceOptions": {
          "calcs": [
            "lastNotNull"
          ],
          "fields": "/^status \\{host=\"6a7bddf72769\", topic=\"rsa/seismic/smart/NOM00/telemetry/state\"\\}$/",
          "values": false
        },
        "showPercentChange": false,
        "textMode": "auto",
        "wideLayout": true
      },
      "pluginVersion": "11.2.0",
      "targets": [
        {
          "datasource": {
            "type": "influxdb",
            "uid": "bf4fhga3fgvswc"
          },
          "query": "from(bucket: \"rsa\")\r\n  |> range(start: -10m)\r\n  |> filter(fn: (r) => r._measurement == \"mqtt_consumer\")\r\n  |> filter(fn: (r) => r._field == \"status\")\r\n  |> last()\r\n",
          "refId": "A"
        }
      ],
      "title": "Estado de la estación",
      "type": "stat"
    },
    {
      "datasource": {
        "default": true,
        "type": "influxdb",
        "uid": "bf4fhga3fgvswc"
      },
      "fieldConfig": {
        "defaults": {
          "color": {
            "mode": "thresholds"
          },
          "mappings": [],
          "thresholds": {
            "mode": "absolute",
            "steps": [
              {
                "color": "green",
                "value": null
              },
              {
                "color": "yellow",
                "value": 0
              }
            ]
          },
          "unit": "decgbytes"
        },
        "overrides": []
      },
      "gridPos": {
        "h": 8,
        "w": 12,
        "x": 12,
        "y": 0
      },
      "id": 4,
      "options": {
        "colorMode": "value",
        "graphMode": "area",
        "justifyMode": "auto",
        "orientation": "auto",
        "percentChangeColorMode": "standard",
        "reduceOptions": {
          "calcs": [
            "lastNotNull"
          ],
          "fields": "",
          "values": false
        },
        "showPercentChange": false,
        "textMode": "auto",
        "wideLayout": true
      },
      "pluginVersion": "11.2.0",
      "targets": [
        {
          "datasource": {
            "type": "influxdb",
            "uid": "bf4fhga3fgvswc"
          },
          "query": "from(bucket: \"rsa\")\r\n  |> range(start: -1h)\r\n  |> filter(fn: (r) => r._field == \"disk_free_gb\")\r\n  |> filter(fn: (r) => r.topic =~ /telemetry\\/health/)\r\n  |> last()\r\n",
          "refId": "A"
        }
      ],
      "title": "Espacio libre de disco GB",
      "type": "stat"
    },
    {
      "datasource": {
        "default": true,
        "type": "influxdb",
        "uid": "bf4fhga3fgvswc"
      },
      "description": "Tiempo total (en segundos) que la estación ha permanecido encendida desde su último reinicio.",
      "fieldConfig": {
        "defaults": {
          "color": {
            "mode": "thresholds"
          },
          "mappings": [],
          "thresholds": {
            "mode": "absolute",
            "steps": [
              {
                "color": "green",
                "value": null
              },
              {
                "color": "red",
                "value": 80
              }
            ]
          }
        },
        "overrides": []
      },
      "gridPos": {
        "h": 8,
        "w": 12,
        "x": 0,
        "y": 8
      },
      "id": 3,
      "options": {
        "colorMode": "value",
        "graphMode": "area",
        "justifyMode": "auto",
        "orientation": "auto",
        "percentChangeColorMode": "standard",
        "reduceOptions": {
          "calcs": [
            "lastNotNull"
          ],
          "fields": "",
          "values": false
        },
        "showPercentChange": false,
        "textMode": "auto",
        "wideLayout": true
      },
      "pluginVersion": "11.2.0",
      "targets": [
        {
          "datasource": {
            "type": "influxdb",
            "uid": "bf4fhga3fgvswc"
          },
          "query": "from(bucket: \"rsa\")\r\n  |> range(start: -1h)\r\n  |> filter(fn: (r) => r._field == \"uptime_s\")\r\n  |> filter(fn: (r) => r.topic =~ /telemetry\\/health/)\r\n  |> last()\r\n",
          "refId": "A"
        }
      ],
      "title": "Tiempo encendido",
      "type": "stat"
    },
    {
      "datasource": {
        "default": true,
        "type": "influxdb",
        "uid": "bf4fhga3fgvswc"
      },
      "fieldConfig": {
        "defaults": {
          "color": {
            "mode": "thresholds"
          },
          "mappings": [],
          "thresholds": {
            "mode": "absolute",
            "steps": [
              {
                "color": "green",
                "value": null
              },
              {
                "color": "blue",
                "value": 0
              }
            ]
          }
        },
        "overrides": []
      },
      "gridPos": {
        "h": 8,
        "w": 12,
        "x": 12,
        "y": 8
      },
      "id": 1,
      "options": {
        "colorMode": "value",
        "graphMode": "area",
        "justifyMode": "auto",
        "orientation": "auto",
        "percentChangeColorMode": "standard",
        "reduceOptions": {
          "calcs": [
            "lastNotNull"
          ],
          "fields": "/^last_event \\{host=\"6a7bddf72769\", topic=\"rsa/seismic/smart/NOM00/telemetry/heartbeat\"\\}$/",
          "values": false
        },
        "showPercentChange": false,
        "textMode": "auto",
        "wideLayout": true
      },
      "pluginVersion": "11.2.0",
      "targets": [
        {
          "datasource": {
            "type": "influxdb",
            "uid": "bf4fhga3fgvswc"
          },
          "query": "from(bucket: \"rsa\")\r\n  |> range(start: -1h)\r\n  |> filter(fn: (r) => r._field == \"last_event\")\r\n  |> filter(fn: (r) => r.topic =~ /telemetry\\/heartbeat/)\r\n  |> last()\r\n",
          "refId": "A"
        }
      ],
      "title": "Último evento",
      "type": "stat"
    },
    {
      "datasource": {
        "default": true,
        "type": "influxdb",
        "uid": "bf4fhga3fgvswc"
      },
      "description": "Muestra la temperatura de la estación",
      "fieldConfig": {
        "defaults": {
          "color": {
            "mode": "thresholds"
          },
          "mappings": [],
          "thresholds": {
            "mode": "absolute",
            "steps": [
              {
                "color": "green",
                "value": null
              },
              {
                "color": "blue",
                "value": 0
              }
            ]
          },
          "unit": "celsius"
        },
        "overrides": []
      },
      "gridPos": {
        "h": 8,
        "w": 12,
        "x": 0,
        "y": 16
      },
      "id": 2,
      "options": {
        "colorMode": "value",
        "graphMode": "area",
        "justifyMode": "auto",
        "orientation": "auto",
        "percentChangeColorMode": "standard",
        "reduceOptions": {
          "calcs": [
            "lastNotNull"
          ],
          "fields": "",
          "values": false
        },
        "showPercentChange": false,
        "textMode": "auto",
        "wideLayout": true
      },
      "pluginVersion": "11.2.0",
      "targets": [
        {
          "datasource": {
            "type": "influxdb",
            "uid": "bf4fhga3fgvswc"
          },
          "query": "from(bucket: \"rsa\")\r\n  |> range(start: -1h)\r\n  |> filter(fn: (r) => r._field == \"temp\")\r\n  |> last()\r\n",
          "refId": "A"
        }
      ],
      "title": "Temperatura de la estación °C",
      "type": "stat"
    }
  ],
  "schemaVersion": 39,
  "tags": [],
  "templating": {
    "list": []
  },
  "time": {
    "from": "now-5m",
    "to": "now"
  },
  "timepicker": {
    "refresh_intervals": [
      "30s"
    ]
  },
  "timezone": "browser",
  "title": "New dashboard",
  "uid": "bf4fm9dlaw8aoe",
  "version": 8,
  "weekStart": ""
}